differt2d/__init__.py
differt2d/__version__.py
differt2d/_typing.py
differt2d/abc.py
differt2d/defaults.py
differt2d/geometry.py
differt2d/logic.py
differt2d/optimize.py
differt2d/scene.py
differt2d/utils.py
differt2d-0.4.0.dist-info/METADATA
differt2d-0.4.0.dist-info/WHEEL
differt2d-0.4.0.dist-info/licenses/LICENSE.md
differt2d-0.4.0.dist-info/RECORD
