Metadata-Version: 2.4
Name: DiffeRT2d
Version: 0.4.0
Summary: 2D Toolbox for Differentiable Ray Tracing
Project-URL: Changelog, https://github.com/jeertmans/DiffeRT2d/releases
Project-URL: Documentation, https://eertmans.be/DiffeRT2d
Project-URL: Founding, https://github.com/sponsors/jeertmans
Project-URL: Homepage, https://github.com/jeertmans/DiffeRT2d
Project-URL: Repository, https://github.com/jeertmans/DiffeRT2d
Author-email: Jérome Eertmans <jeertmans@icloud.com>
License-Expression: MIT
License-File: LICENSE.md
Keywords: differentiable,ray tracing
Classifier: License :: OSI Approved :: MIT License
Classifier: Operating System :: OS Independent
Classifier: Programming Language :: Python :: 3
Classifier: Programming Language :: Python :: 3.10
Classifier: Programming Language :: Python :: 3.11
Classifier: Programming Language :: Python :: 3.12
Classifier: Topic :: Scientific/Engineering
Requires-Python: >=3.10
Requires-Dist: beartype>=0.20
Requires-Dist: differt-core==0.0.31
Requires-Dist: equinox>=0.11.5
Requires-Dist: jax>=0.4.32
Requires-Dist: jaxtyping>=0.2.24
Requires-Dist: matplotlib>=3.7.1
Requires-Dist: numpy>=1.24
Requires-Dist: optax>=0.1.7
Requires-Dist: typing-extensions>=4.9.0; python_version < '3.11'
